ymm/__init__.py
ymm/cli.py
ymm/file.py
ymm/keys.py
ymm/scope.py
ymm/ymm.py
ymm-0.6.1.dist-info/LICENSE
ymm-0.6.1.dist-info/METADATA
ymm-0.6.1.dist-info/WHEEL
ymm-0.6.1.dist-info/entry_points.txt
ymm-0.6.1.dist-info/top_level.txt
ymm-0.6.1.dist-info/RECORD
