Metadata-Version: 2.1
Name: ymm
Version: 0.6.1
Summary: Composable Query Meta Language
Home-page: https://github.com/TheSwanFactory/ymm
Author: Ernest Prabhakar
Author-email: ernest.prabhakar@gmail.com
License: UNKNOWN
Project-URL: Bug Tracker, https://github.com/TheSwanFactory/ymm/issues
Platform: UNKNOWN
Classifier: Programming Language :: Python :: 3
Classifier: License :: OSI Approved :: MIT License
Classifier: Operating System :: OS Independent
Requires-Python: >=3.6
License-File: LICENSE
Requires-Dist: jmespath
